[
    {
        "name": "1981 Fleer Team Action",
        "sid": "8893"
    },
    {
        "name": "1981 Topps",
        "sid": "3232"
    },
    {
        "name": "1981 JOGO",
        "sid": "76246"
    },
    {
        "name": "1981 Red Rooster Calgary Stampeders",
        "sid": "88635"
    },
    {
        "name": "1981 Red Rooster Edmonton Eskimos",
        "sid": "110006"
    },
    {
        "name": "1981 Saskatchewan Roughriders Police",
        "sid": "110057"
    },
    {
        "name": "1981 Arizona Wildcats Police",
        "sid": "110743"
    },
    {
        "name": "1981 Louisville Cardinals Police",
        "sid": "245169"
    },
    {
        "name": "1981 Coca-Cola Caps",
        "sid": "183435"
    },
    {
        "name": "1981 Holsum Discs",
        "sid": "99936"
    },
    {
        "name": "1981 Topps Coca-Cola Baltimore Colts",
        "sid": "77110"
    },
    {
        "name": "1981 Topps Coca-Cola Dallas Cowboys",
        "sid": "77111"
    },
    {
        "name": "1981 Topps Coca-Cola Houston Oilers",
        "sid": "77112"
    },
    {
        "name": "1981 Topps Coca-Cola New York Giants",
        "sid": "77113"
    },
    {
        "name": "1981 Topps Coca-Cola San Diego Chargers",
        "sid": "77115"
    },
    {
        "name": "1981 Topps Coca-Cola St. Louis Cardinals",
        "sid": "77114"
    },
    {
        "name": "1981 Topps Coca-Cola Washington Redskins",
        "sid": "77116"
    },
    {
        "name": "1981 Marketcom Mini-Poster",
        "sid": "82882"
    },
    {
        "name": "1981 TCMA Greats",
        "sid": "91649"
    },
    {
        "name": "1981 Topps Dallas Cowboys Cheerleaders",
        "sid": "81040"
    },
    {
        "name": "1981 Topps Red Border Stickers",
        "sid": "183420"
    },
    {
        "name": "1981 Topps Stickers",
        "sid": "81515"
    },
    {
        "name": "1981 Atlanta Falcons Police",
        "sid": "221887"
    },
    {
        "name": "1981 Chicago Bears Police",
        "sid": "110757"
    },
    {
        "name": "1981 Dallas Cowboys Police",
        "sid": "221625"
    },
    {
        "name": "1981 Kansas City Chiefs Police",
        "sid": "147711"
    },
    {
        "name": "1981 Miami Dolphins Police",
        "sid": "309945"
    },
    {
        "name": "1981 New York Jets Police",
        "sid": "111021"
    },
    {
        "name": "1981 Pittsburgh Steelers Police",
        "sid": "90387"
    },
    {
        "name": "1981 San Diego Chargers Police",
        "sid": "109967"
    }
]